CLI/CompareLS.py
CLI/CompareLSOutput.py
CLI/LSVector.py
CLI/SearchLS.py
CLI/SearchLSOutput.py
CLI/SearchSQ.py
CLI/SearchSQOutput.py
CLI/__init__.py
CLI/compare.py
CLI/family_list.py
CLI/get_metric.py
CLI/load_files.py
CLI/output_results.py
CLI/search.py
CLI/search_lat.py
CLI/search_seq.py
CLI/seq_lengths.csv
CLI/Latent_spaces/3MG2_OGT.txt
CLI/Latent_spaces/AAEX_YAGP.txt
CLI/Latent_spaces/AAEX_YBHG.txt
CLI/Latent_spaces/ACCC_BCCP.txt
CLI/Latent_spaces/ACCC_HOA.txt
CLI/Latent_spaces/ACCC_PABA.txt
CLI/Latent_spaces/ACCC_PUR3.txt
CLI/Latent_spaces/ACCC_PUR5.txt
CLI/Latent_spaces/ACCC_PYRB.txt
CLI/Latent_spaces/ACCC_PYRC.txt
CLI/Latent_spaces/ACCD_FOLC.txt
CLI/Latent_spaces/ACPS_ALR1.txt
CLI/Latent_spaces/ACPS_CHPB.txt
CLI/Latent_spaces/ACPS_ERA.txt
CLI/Latent_spaces/ACPS_FECI.txt
CLI/Latent_spaces/ACPS_PDXJ.txt
CLI/Latent_spaces/ACPS_RNC.txt
CLI/Latent_spaces/ACP_BCCP.txt
CLI/Latent_spaces/ACP_FABD.txt
CLI/Latent_spaces/ACP_FABF.txt
CLI/Latent_spaces/ACP_FABZ.txt
CLI/Latent_spaces/ACP_FADM.txt
CLI/Latent_spaces/ACP_HOLA.txt
CLI/Latent_spaces/ACP_HOLB.txt
CLI/Latent_spaces/ACP_KTHY.txt
CLI/Latent_spaces/ACP_PABC.txt
CLI/Latent_spaces/ACP_PLSX.txt
CLI/Latent_spaces/ACP_RNC.txt
CLI/Latent_spaces/ACP_RSUA.txt
CLI/Latent_spaces/ACP_SLYA.txt
CLI/Latent_spaces/ACP_YCED.txt
CLI/Latent_spaces/ACP_YCEF.txt
CLI/Latent_spaces/ACP_YCEG.txt
CLI/Latent_spaces/ACRB_ACRR.txt
CLI/Latent_spaces/ACRE_ENVR.txt
CLI/Latent_spaces/AGAA_AGAI.txt
CLI/Latent_spaces/AGAA_ALSK.txt
CLI/Latent_spaces/ALDB_BETA.txt
CLI/Latent_spaces/ALKH_FRLD.txt
CLI/Latent_spaces/ALSB_ALSC.txt
CLI/Latent_spaces/ALSB_FOLC.txt
CLI/Latent_spaces/ALSB_RRAA.txt
CLI/Latent_spaces/ALSE_DEF.txt
CLI/Latent_spaces/ALSE_RSGA.txt
CLI/Latent_spaces/ALSE_RSMB.txt
CLI/Latent_spaces/AMIA_YJEE.txt
CLI/Latent_spaces/AMPE_HIS8.txt
CLI/Latent_spaces/AMTB_GLNK.txt
CLI/Latent_spaces/APAG_PPIC.txt
CLI/Latent_spaces/APPB_APPC.txt
CLI/Latent_spaces/APT_DTD.txt
CLI/Latent_spaces/APT_FRE.txt
CLI/Latent_spaces/APT_PYRF.txt
compbiolab_CLI-0.4.0.dist-info/LICENSE
compbiolab_CLI-0.4.0.dist-info/METADATA
compbiolab_CLI-0.4.0.dist-info/WHEEL
compbiolab_CLI-0.4.0.dist-info/entry_points.txt
compbiolab_CLI-0.4.0.dist-info/top_level.txt
compbiolab_CLI-0.4.0.dist-info/RECORD
