Metadata-Version: 2.1
Name: compbiolab-CLI
Version: 0.4.0
Summary: CLI tool to compare and search protein families
Home-page: https://github.com/cfogel/CLI/
Download-URL: https://pypi.org/project/compbiolab-CLI/
Author: compbiolab
License: MIT
Project-URL: Documentation, https://cfogel.github.io/compbiolab-CLI-docs/
Platform: any
Classifier: Development Status :: 3 - Alpha
Classifier: Programming Language :: Python :: 3
Classifier: Programming Language :: Python :: 3.7
Classifier: Programming Language :: Python :: 3.8
Classifier: Programming Language :: Python :: 3.9
Classifier: Programming Language :: Python :: 3.10
Classifier: License :: OSI Approved :: MIT License
Classifier: Operating System :: OS Independent
Classifier: Intended Audience :: Science/Research
Requires-Python: >=3.7
License-File: LICENSE
Requires-Dist: argparse-formatter
Requires-Dist: numpy (<1.19.0,>=1.16.0)
Requires-Dist: pandas (>=1.1.4)
Requires-Dist: scipy (>=1.4.1)
Requires-Dist: tqdm
Requires-Dist: importlib-resources (>=1.1.0) ; python_version < "3.9"
Requires-Dist: h5py (==2.10.0) ; python_version == "3.7"
Requires-Dist: keras (==2.3.1) ; python_version == "3.7"
Requires-Dist: silence-tensorflow ; python_version == "3.7"
Requires-Dist: tensorflow (==1.15.4) ; python_version == "3.7"
